{
  "metadata": {
    "id": "final_boss_194",
    "axes": {
      "c_max": 100,
      "t_max": 1200
    }
  },
  "nodes": {
    "top_L": {
      "c": 0,
      "t": 1200,
      "bounds": {
        "lock_t": true,
        "lock_c": true
      }
    },
    "top_R": {
      "c": 100,
      "t": 1200,
      "bounds": {
        "lock_t": true,
        "lock_c": true
      }
    },
    "bot_L": {
      "c": 0,
      "t": 0,
      "bounds": {
        "lock_t": true,
        "lock_c": true
      }
    },
    "bot_R": {
      "c": 100,
      "t": 0,
      "bounds": {
        "lock_t": true,
        "lock_c": true
      }
    },
    "tmA": {
      "c": 0,
      "t": 1065.450384094911,
      "bounds": {
        "lock_c": true,
        "t_min": 1000,
        "t_max": 1200
      }
    },
    "tmB": {
      "c": 100,
      "t": 1104.0640015964696,
      "bounds": {
        "lock_c": true,
        "t_min": 1000,
        "t_max": 1200
      }
    },
    "im1_t": {
      "c": 59.96630652175823,
      "t": 1175.5231359306629,
      "bounds": {
        "lock_c": true,
        "t_min": 1000,
        "t_max": 1200
      }
    },
    "im1_b": {
      "c": 59.96630652175823,
      "t": 0,
      "bounds": {
        "lock_c": true,
        "lock_t": true
      }
    },
    "e1_a": {
      "c": 11.736226531755072,
      "t": 844.7217128303254,
      "bounds": {
        "lock_t": true,
        "c_min": 2,
        "c_max": 18
      }
    },
    "e1_l": {
      "c": 38.82574096915673,
      "t": 844.7217128303254,
      "bounds": {
        "lock_t": true,
        "c_min": 25,
        "c_max": 50
      }
    },
    "im1_e1": {
      "c": 59.96630652175823,
      "t": 844.7217128303254,
      "bounds": {
        "lock_c": true,
        "lock_t": true
      }
    },
    "po_nexus": {
      "c": 21.03614959607141,
      "t": 661.1308804229789,
      "bounds": {
        "lock_c": true,
        "lock_t": true
      }
    },
    "im2_b": {
      "c": 21.03614959607141,
      "t": 0,
      "bounds": {
        "lock_c": true,
        "lock_t": true
      }
    },
    "p_im1": {
      "c": 59.96630652175823,
      "t": 962.0309019109568,
      "bounds": {
        "lock_c": true,
        "lock_t": true
      }
    },
    "p_g": {
      "c": 71.5496478533305,
      "t": 962.0309019109568,
      "bounds": {
        "lock_t": true,
        "c_min": 61.96630652175823,
        "c_max": 79.39476498752681
      }
    },
    "p_l": {
      "c": 81.39476498752681,
      "t": 962.0309019109568,
      "bounds": {
        "lock_t": true,
        "c_min": 73.5496478533305,
        "c_max": 90
      }
    },
    "e2_g": {
      "c": 74.40908157856609,
      "t": 733.5334816475018,
      "bounds": {
        "lock_t": true,
        "c_min": 73.5496478533305,
        "c_max": 77.32656067735056
      }
    },
    "e2_l": {
      "c": 79.32656067735056,
      "t": 733.5334816475018,
      "bounds": {
        "lock_t": true,
        "c_min": 76.40908157856609,
        "c_max": 94.78597712387933
      }
    },
    "e2_e": {
      "c": 96.78597712387933,
      "t": 733.5334816475018,
      "bounds": {
        "lock_t": true,
        "c_min": 81.32656067735056,
        "c_max": 98
      }
    },
    "im1_eu": {
      "c": 59.96630652175823,
      "t": 585.0326073270497,
      "bounds": {
        "lock_c": true,
        "lock_t": true
      }
    },
    "eu_nexus": {
      "c": 72.8291105008468,
      "t": 585.0326073270497,
      "bounds": {
        "lock_t": true,
        "c_min": 64.96630652175823,
        "c_max": 92.83370880001813
      }
    },
    "eu_e_iso": {
      "c": 97.83370880001813,
      "t": 585.0326073270497,
      "bounds": {
        "lock_t": true,
        "c_min": 74.8291105008468,
        "c_max": 99
      }
    },
    "t_a": {
      "c": 2.0215897542537418,
      "t": 0,
      "bounds": {
        "lock_t": true,
        "c_min": 0.1,
        "c_max": 19.03614959607141
      }
    },
    "t_e": {
      "c": 98.8296840358591,
      "t": 0,
      "bounds": {
        "lock_t": true,
        "c_min": 97.93370880001812,
        "c_max": 99.9
      }
    }
  },
  "curves": {
    "L_1": {
      "start": "tmA",
      "end": "e1_l",
      "type": "liquidus"
    },
    "L_2": {
      "start": "e1_l",
      "end": "im1_t",
      "type": "liquidus"
    },
    "L_3": {
      "start": "im1_t",
      "end": "p_l",
      "type": "liquidus"
    },
    "L_4": {
      "start": "p_l",
      "end": "e2_l",
      "type": "liquidus"
    },
    "L_5": {
      "start": "e2_l",
      "end": "tmB",
      "type": "liquidus"
    },
    "S_a": {
      "start": "tmA",
      "end": "e1_a",
      "type": "solidus"
    },
    "S_g": {
      "start": "p_g",
      "end": "e2_g",
      "type": "solidus"
    },
    "S_e": {
      "start": "tmB",
      "end": "e2_e",
      "type": "solidus"
    },
    "sol_a_up": {
      "start": "e1_a",
      "end": "po_nexus",
      "type": "solvus"
    },
    "sol_a_bot": {
      "start": "po_nexus",
      "end": "t_a",
      "type": "solvus"
    },
    "sol_g_L": {
      "start": "p_g",
      "end": "eu_nexus",
      "type": "solvus"
    },
    "sol_g_R": {
      "start": "e2_g",
      "end": "eu_nexus",
      "type": "solvus"
    },
    "sol_e": {
      "start": "e2_e",
      "end": "t_e",
      "type": "solvus"
    },
    "IM1": {
      "start": "im1_t",
      "end": "im1_b",
      "type": "vertical"
    },
    "IM2": {
      "start": "po_nexus",
      "end": "im2_b",
      "type": "vertical"
    },
    "iso_e1": {
      "start": "e1_a",
      "end": "im1_e1",
      "type": "horizontal"
    },
    "iso_p": {
      "start": "p_im1",
      "end": "p_l",
      "type": "horizontal"
    },
    "iso_e2": {
      "start": "e2_g",
      "end": "e2_e",
      "type": "horizontal"
    },
    "iso_eu": {
      "start": "im1_eu",
      "end": "eu_e_iso",
      "type": "horizontal"
    },
    "edge_L_top": {
      "start": "top_L",
      "end": "tmA",
      "type": "edge"
    },
    "edge_L_bot": {
      "start": "tmA",
      "end": "bot_L",
      "type": "edge"
    },
    "edge_R_top": {
      "start": "top_R",
      "end": "tmB",
      "type": "edge"
    },
    "edge_R_bot": {
      "start": "tmB",
      "end": "bot_R",
      "type": "edge"
    },
    "edge_top": {
      "start": "top_L",
      "end": "top_R",
      "type": "edge"
    },
    "b_0_a": {
      "start": "bot_L",
      "end": "t_a",
      "type": "edge"
    },
    "b_a_im2": {
      "start": "t_a",
      "end": "im2_b",
      "type": "edge"
    },
    "b_im2_im1": {
      "start": "im2_b",
      "end": "im1_b",
      "type": "edge"
    },
    "b_im1_e": {
      "start": "im1_b",
      "end": "t_e",
      "type": "edge"
    },
    "b_e_100": {
      "start": "t_e",
      "end": "bot_R",
      "type": "edge"
    }
  },
  "regions": {
    "R_L": {
      "type": "single-phase",
      "phase_name": "L",
      "bounding_curves": [
        {
          "id": "L_1",
          "dir": 1
        },
        {
          "id": "L_2",
          "dir": 1
        },
        {
          "id": "L_3",
          "dir": 1
        },
        {
          "id": "L_4",
          "dir": 1
        },
        {
          "id": "L_5",
          "dir": 1
        },
        {
          "id": "edge_R_top",
          "dir": -1
        },
        {
          "id": "edge_top",
          "dir": -1
        },
        {
          "id": "edge_L_top",
          "dir": 1
        }
      ]
    },
    "R_a": {
      "type": "single-phase",
      "phase_name": "\u03b1",
      "bounding_curves": [
        {
          "id": "S_a",
          "dir": -1
        },
        {
          "id": "edge_L_bot",
          "dir": 1
        },
        {
          "id": "b_0_a",
          "dir": 1
        },
        {
          "id": "sol_a_bot",
          "dir": -1
        },
        {
          "id": "sol_a_up",
          "dir": -1
        }
      ]
    },
    "R_g": {
      "type": "single-phase",
      "phase_name": "\u03b3",
      "bounding_curves": [
        {
          "id": "sol_g_L",
          "dir": 1
        },
        {
          "id": "sol_g_R",
          "dir": -1
        },
        {
          "id": "S_g",
          "dir": -1
        }
      ]
    },
    "R_e": {
      "type": "single-phase",
      "phase_name": "\u03b5",
      "bounding_curves": [
        {
          "id": "S_e",
          "dir": 1
        },
        {
          "id": "edge_R_bot",
          "dir": 1
        },
        {
          "id": "b_e_100",
          "dir": -1
        },
        {
          "id": "sol_e",
          "dir": -1
        }
      ]
    },
    "R_La": {
      "type": "two-phase",
      "phases": [
        "L",
        "\u03b1"
      ],
      "bounding_curves": [
        {
          "id": "L_1",
          "dir": -1
        },
        {
          "id": "S_a",
          "dir": 1
        },
        {
          "id": "iso_e1",
          "dir": 1
        }
      ]
    },
    "R_L_IM1_L": {
      "type": "two-phase",
      "phases": [
        "L",
        "IM1"
      ],
      "bounding_curves": [
        {
          "id": "L_2",
          "dir": -1
        },
        {
          "id": "iso_e1",
          "dir": -1
        },
        {
          "id": "IM1",
          "dir": 1
        }
      ]
    },
    "R_L_IM1_R": {
      "type": "two-phase",
      "phases": [
        "L",
        "IM1"
      ],
      "bounding_curves": [
        {
          "id": "L_3",
          "dir": 1
        },
        {
          "id": "iso_p",
          "dir": -1
        },
        {
          "id": "IM1",
          "dir": -1
        }
      ]
    },
    "R_L_g": {
      "type": "two-phase",
      "phases": [
        "L",
        "\u03b3"
      ],
      "bounding_curves": [
        {
          "id": "L_4",
          "dir": -1
        },
        {
          "id": "iso_e2",
          "dir": -1
        },
        {
          "id": "S_g",
          "dir": 1
        },
        {
          "id": "iso_p",
          "dir": 1
        }
      ]
    },
    "R_L_e": {
      "type": "two-phase",
      "phases": [
        "L",
        "\u03b5"
      ],
      "bounding_curves": [
        {
          "id": "L_5",
          "dir": -1
        },
        {
          "id": "S_e",
          "dir": 1
        },
        {
          "id": "iso_e2",
          "dir": 1
        }
      ]
    },
    "R_a_IM1": {
      "type": "two-phase",
      "phases": [
        "\u03b1",
        "IM1"
      ],
      "bounding_curves": [
        {
          "id": "sol_a_up",
          "dir": 1
        },
        {
          "id": "iso_e1",
          "dir": 1
        },
        {
          "id": "IM1",
          "dir": 1
        }
      ]
    },
    "R_a_IM2": {
      "type": "two-phase",
      "phases": [
        "\u03b1",
        "IM2"
      ],
      "bounding_curves": [
        {
          "id": "sol_a_bot",
          "dir": 1
        },
        {
          "id": "b_a_im2",
          "dir": 1
        },
        {
          "id": "IM2",
          "dir": -1
        }
      ]
    },
    "R_IM2_IM1": {
      "type": "two-phase",
      "phases": [
        "IM2",
        "IM1"
      ],
      "bounding_curves": [
        {
          "id": "IM2",
          "dir": 1
        },
        {
          "id": "b_im2_im1",
          "dir": 1
        },
        {
          "id": "IM1",
          "dir": -1
        }
      ]
    },
    "R_IM1_g": {
      "type": "two-phase",
      "phases": [
        "IM1",
        "\u03b3"
      ],
      "bounding_curves": [
        {
          "id": "IM1",
          "dir": 1
        },
        {
          "id": "iso_p",
          "dir": -1
        },
        {
          "id": "S_g",
          "dir": 1
        },
        {
          "id": "sol_g_L",
          "dir": 1
        }
      ]
    },
    "R_g_e": {
      "type": "two-phase",
      "phases": [
        "\u03b3",
        "\u03b5"
      ],
      "bounding_curves": [
        {
          "id": "sol_g_R",
          "dir": 1
        },
        {
          "id": "iso_e2",
          "dir": 1
        },
        {
          "id": "sol_e",
          "dir": -1
        },
        {
          "id": "iso_eu",
          "dir": -1
        }
      ]
    },
    "R_IM1_e": {
      "type": "two-phase",
      "phases": [
        "IM1",
        "\u03b5"
      ],
      "bounding_curves": [
        {
          "id": "IM1",
          "dir": 1
        },
        {
          "id": "b_im1_e",
          "dir": 1
        },
        {
          "id": "sol_e",
          "dir": -1
        },
        {
          "id": "iso_eu",
          "dir": -1
        }
      ]
    }
  }
}